py.typed
orq_poc_python_client/__init__.py
orq_poc_python_client/_hooks/__init__.py
orq_poc_python_client/_hooks/registration.py
orq_poc_python_client/_hooks/sdkhooks.py
orq_poc_python_client/_hooks/types.py
orq_poc_python_client/_version.py
orq_poc_python_client/basesdk.py
orq_poc_python_client/chat.py
orq_poc_python_client/completions.py
orq_poc_python_client/contacts.py
orq_poc_python_client/deployments_sdk.py
orq_poc_python_client/embeddings.py
orq_poc_python_client/feedback.py
orq_poc_python_client/files.py
orq_poc_python_client/httpclient.py
orq_poc_python_client/images.py
orq_poc_python_client/metrics.py
orq_poc_python_client/models/__init__.py
orq_poc_python_client/models/bulkfileuploadop.py
orq_poc_python_client/models/createcontactop.py
orq_poc_python_client/models/createfeedbackop.py
orq_poc_python_client/models/deploymentcreatemetricop.py
orq_poc_python_client/models/deploymentgetconfigop.py
orq_poc_python_client/models/deploymentinvokeop.py
orq_poc_python_client/models/deployments.py
orq_poc_python_client/models/deploymentsop.py
orq_poc_python_client/models/fileuploadop.py
orq_poc_python_client/models/honoapierror.py
orq_poc_python_client/models/remoteconfigsgetconfigop.py
orq_poc_python_client/models/routerchatcompletionsop.py
orq_poc_python_client/models/routercompletionsop.py
orq_poc_python_client/models/routerembeddingop.py
orq_poc_python_client/models/routerimagegenerationsop.py
orq_poc_python_client/models/routerrerankop.py
orq_poc_python_client/models/sdkerror.py
orq_poc_python_client/models/security.py
orq_poc_python_client/orq_completions.py
orq_poc_python_client/py.typed
orq_poc_python_client/remoteconfig.py
orq_poc_python_client/router.py
orq_poc_python_client/sdk.py
orq_poc_python_client/sdkconfiguration.py
orq_poc_python_client/types/__init__.py
orq_poc_python_client/types/basemodel.py
orq_poc_python_client/utils/__init__.py
orq_poc_python_client/utils/annotations.py
orq_poc_python_client/utils/enums.py
orq_poc_python_client-0.5.1.dist-info/METADATA
orq_poc_python_client-0.5.1.dist-info/WHEEL
orq_poc_python_client-0.5.1.dist-info/RECORD
